draxutils/__init__.py
draxutils/hgf_multiproc.py
draxutils/html_util.py
draxutils/iou.py
draxutils/timer.py
draxutils/vis_utils.py
draxutils/wdb.py
draxutils-0.1.15.dist-info/METADATA
draxutils-0.1.15.dist-info/WHEEL
draxutils-0.1.15.dist-info/top_level.txt
draxutils-0.1.15.dist-info/RECORD
