Metadata-Version: 2.1
Name: draxutils
Version: 0.1.15
Summary: Utility functions for image handling
Author: dddraxxx
Author-email: dongqh078@gmail.com
Classifier: Programming Language :: Python :: 3
Classifier: License :: OSI Approved :: MIT License
Classifier: Operating System :: OS Independent
Requires-Python: >=3.6
Requires-Dist: pandas
Requires-Dist: pillow
Requires-Dist: datasets
Requires-Dist: IPython
Requires-Dist: wandb
Requires-Dist: tqdm
Requires-Dist: numpy
